[
{ "seq_id" : 52, "qsl_idx" : 43339, "data" : "82020000" },
{ "seq_id" : 53, "qsl_idx" : 20363, "data" : "33020000" },
{ "seq_id" : 54, "qsl_idx" : 21021, "data" : "DA000000" },
{ "seq_id" : 55, "qsl_idx" : 49128, "data" : "D4000000" },
{ "seq_id" : 56, "qsl_idx" : 20754, "data" : "AD010000" },
{ "seq_id" : 57, "qsl_idx" : 20675, "data" : "E6000000" },
{ "seq_id" : 58, "qsl_idx" : 20630, "data" : "9F020000" },
{ "seq_id" : 59, "qsl_idx" : 34971, "data" : "48000000" },
{ "seq_id" : 60, "qsl_idx" : 36830, "data" : "32030000" },
{ "seq_id" : 61, "qsl_idx" : 30186, "data" : "B4020000" },
{ "seq_id" : 62, "qsl_idx" : 3377, "data" : "79000000" },
{ "seq_id" : 63, "qsl_idx" : 38169, "data" : "34010000" },
{ "seq_id" : 64, "qsl_idx" : 15993, "data" : "22030000" },
{ "seq_id" : 65, "qsl_idx" : 35335, "data" : "C3020000" },
{ "seq_id" : 66, "qsl_idx" : 29636, "data" : "33020000" },
{ "seq_id" : 67, "qsl_idx" : 4621, "data" : "27000000" },
{ "seq_id" : 68, "qsl_idx" : 13331, "data" : "AB010000" },
{ "seq_id" : 69, "qsl_idx" : 38180, "data" : "32010000" },
{ "seq_id" : 70, "qsl_idx" : 34223, "data" : "EB000000" },
{ "seq_id" : 71, "qsl_idx" : 20998, "data" : "36000000" },
{ "seq_id" : 72, "qsl_idx" : 40725, "data" : "87010000" },
{ "seq_id" : 73, "qsl_idx" : 25037, "data" : "6C030000" },
{ "seq_id" : 74, "qsl_idx" : 10443, "data" : "80030000" },
{ "seq_id" : 75, "qsl_idx" : 3065, "data" : "D0020000" },
{ "seq_id" : 76, "qsl_idx" : 30914, "data" : "B4000000" },
{ "seq_id" : 77, "qsl_idx" : 31021, "data" : "05020000" },
{ "seq_id" : 78, "qsl_idx" : 17255, "data" : "51020000" },
{ "seq_id" : 79, "qsl_idx" : 18304, "data" : "2A000000" },
{ "seq_id" : 80, "qsl_idx" : 46072, "data" : "69000000" },
{ "seq_id" : 81, "qsl_idx" : 28566, "data" : "C4010000" },
{ "seq_id" : 82, "qsl_idx" : 30633, "data" : "69030000" },
{ "seq_id" : 83, "qsl_idx" : 4938, "data" : "F1010000" },
{ "seq_id" : 84, "qsl_idx" : 32334, "data" : "81000000" },
{ "seq_id" : 85, "qsl_idx" : 37565, "data" : "5E020000" },
{ "seq_id" : 86, "qsl_idx" : 32459, "data" : "80020000" },
{ "seq_id" : 87, "qsl_idx" : 19746, "data" : "C1000000" },
{ "seq_id" : 88, "qsl_idx" : 33667, "data" : "55010000" },
{ "seq_id" : 89, "qsl_idx" : 10215, "data" : "5E020000" },
{ "seq_id" : 90, "qsl_idx" : 48984, "data" : "77020000" },
{ "seq_id" : 91, "qsl_idx" : 42773, "data" : "7E000000" },
{ "seq_id" : 92, "qsl_idx" : 13239, "data" : "67010000" },
{ "seq_id" : 93, "qsl_idx" : 3637, "data" : "FF000000" },
{ "seq_id" : 94, "qsl_idx" : 17770, "data" : "C2030000" },
{ "seq_id" : 95, "qsl_idx" : 38904, "data" : "E7030000" },
{ "seq_id" : 96, "qsl_idx" : 9897, "data" : "5A010000" },
{ "seq_id" : 97, "qsl_idx" : 753, "data" : "65000000" },
{ "seq_id" : 98, "qsl_idx" : 8310, "data" : "A1000000" },
{ "seq_id" : 99, "qsl_idx" : 33970, "data" : "FA010000" },
{ "seq_id" : 100, "qsl_idx" : 39145, "data" : "CB000000" },
{ "seq_id" : 101, "qsl_idx" : 11702, "data" : "5E030000" },
{ "seq_id" : 102, "qsl_idx" : 47089, "data" : "86020000" },
{ "seq_id" : 103, "qsl_idx" : 8253, "data" : "2D030000" },
{ "seq_id" : 104, "qsl_idx" : 17579, "data" : "B2030000" },
{ "seq_id" : 105, "qsl_idx" : 35004, "data" : "47000000" },
{ "seq_id" : 106, "qsl_idx" : 23116, "data" : "B1030000" },
{ "seq_id" : 107, "qsl_idx" : 24661, "data" : "03020000" },
{ "seq_id" : 108, "qsl_idx" : 45007, "data" : "8B020000" },
{ "seq_id" : 109, "qsl_idx" : 14679, "data" : "DE030000" },
{ "seq_id" : 110, "qsl_idx" : 25959, "data" : "78000000" },
{ "seq_id" : 111, "qsl_idx" : 10983, "data" : "C3030000" },
{ "seq_id" : 112, "qsl_idx" : 18453, "data" : "F7010000" },
{ "seq_id" : 113, "qsl_idx" : 28421, "data" : "05000000" },
{ "seq_id" : 114, "qsl_idx" : 18948, "data" : "3F030000" },
{ "seq_id" : 115, "qsl_idx" : 16997, "data" : "D7000000" },
{ "seq_id" : 116, "qsl_idx" : 37053, "data" : "5B010000" },
{ "seq_id" : 117, "qsl_idx" : 28319, "data" : "0F030000" },
{ "seq_id" : 118, "qsl_idx" : 6095, "data" : "BF030000" },
{ "seq_id" : 119, "qsl_idx" : 10123, "data" : "34020000" },
{ "seq_id" : 120, "qsl_idx" : 15837, "data" : "DA010000" },
{ "seq_id" : 

...

 "9D030000" },
{ "seq_id" : 49944, "qsl_idx" : 17721, "data" : "FA000000" },
{ "seq_id" : 49945, "qsl_idx" : 34841, "data" : "CB030000" },
{ "seq_id" : 49946, "qsl_idx" : 14755, "data" : "1E020000" },
{ "seq_id" : 49947, "qsl_idx" : 15706, "data" : "9C010000" },
{ "seq_id" : 49948, "qsl_idx" : 1637, "data" : "7C020000" },
{ "seq_id" : 49949, "qsl_idx" : 47936, "data" : "AA030000" },
{ "seq_id" : 49950, "qsl_idx" : 11134, "data" : "AB020000" },
{ "seq_id" : 49951, "qsl_idx" : 45548, "data" : "2D010000" },
{ "seq_id" : 49952, "qsl_idx" : 24123, "data" : "6C030000" },
{ "seq_id" : 49953, "qsl_idx" : 23138, "data" : "AB030000" },
{ "seq_id" : 49954, "qsl_idx" : 30458, "data" : "32010000" },
{ "seq_id" : 49955, "qsl_idx" : 39511, "data" : "58020000" },
{ "seq_id" : 49956, "qsl_idx" : 16588, "data" : "D5000000" },
{ "seq_id" : 49957, "qsl_idx" : 4194, "data" : "61030000" },
{ "seq_id" : 49750, "qsl_idx" : 10234, "data" : "5F020000" },
{ "seq_id" : 49751, "qsl_idx" : 37488, "data" : "2B010000" },
{ "seq_id" : 49752, "qsl_idx" : 1914, "data" : "0D000000" },
{ "seq_id" : 49753, "qsl_idx" : 9891, "data" : "C7030000" },
{ "seq_id" : 49754, "qsl_idx" : 42109, "data" : "4B010000" },
{ "seq_id" : 49755, "qsl_idx" : 49572, "data" : "9A020000" },
{ "seq_id" : 49756, "qsl_idx" : 44199, "data" : "BB000000" },
{ "seq_id" : 49757, "qsl_idx" : 39884, "data" : "0D010000" },
{ "seq_id" : 49758, "qsl_idx" : 18931, "data" : "53010000" },
{ "seq_id" : 49759, "qsl_idx" : 20719, "data" : "B6020000" },
{ "seq_id" : 49760, "qsl_idx" : 39207, "data" : "17020000" },
{ "seq_id" : 49761, "qsl_idx" : 44911, "data" : "D8010000" },
{ "seq_id" : 49762, "qsl_idx" : 31195, "data" : "9D010000" },
{ "seq_id" : 49763, "qsl_idx" : 44176, "data" : "C3020000" },
{ "seq_id" : 49764, "qsl_idx" : 8556, "data" : "BE010000" },
{ "seq_id" : 49765, "qsl_idx" : 22479, "data" : "88030000" },
{ "seq_id" : 49766, "qsl_idx" : 21323, "data" : "8E020000" },
{ "seq_id" : 49767, "qsl_idx" : 7087, "data" : "98000000" },
{ "seq_id" : 49768, "qsl_idx" : 2052, "data" : "DF010000" },
{ "seq_id" : 49769, "qsl_idx" : 42560, "data" : "EB000000" },
{ "seq_id" : 49770, "qsl_idx" : 20612, "data" : "AB000000" },
{ "seq_id" : 49771, "qsl_idx" : 45949, "data" : "BB030000" },
{ "seq_id" : 49772, "qsl_idx" : 26404, "data" : "FC010000" },
{ "seq_id" : 49773, "qsl_idx" : 41096, "data" : "23010000" },
{ "seq_id" : 49774, "qsl_idx" : 18116, "data" : "FF010000" },
{ "seq_id" : 49775, "qsl_idx" : 30357, "data" : "63010000" },
{ "seq_id" : 49958, "qsl_idx" : 47516, "data" : "7C020000" },
{ "seq_id" : 49959, "qsl_idx" : 10074, "data" : "18010000" },
{ "seq_id" : 49960, "qsl_idx" : 33176, "data" : "16010000" },
{ "seq_id" : 49961, "qsl_idx" : 11451, "data" : "AB020000" },
{ "seq_id" : 49962, "qsl_idx" : 3024, "data" : "72020000" },
{ "seq_id" : 49963, "qsl_idx" : 49697, "data" : "48030000" },
{ "seq_id" : 49964, "qsl_idx" : 40142, "data" : "34030000" },
{ "seq_id" : 49965, "qsl_idx" : 5841, "data" : "D9000000" },
{ "seq_id" : 49966, "qsl_idx" : 41523, "data" : "F5000000" },
{ "seq_id" : 49967, "qsl_idx" : 7997, "data" : "1B000000" },
{ "seq_id" : 49968, "qsl_idx" : 49216, "data" : "69000000" },
{ "seq_id" : 49969, "qsl_idx" : 49881, "data" : "D6030000" },
{ "seq_id" : 49970, "qsl_idx" : 31290, "data" : "3A030000" },
{ "seq_id" : 49971, "qsl_idx" : 45052, "data" : "FB020000" },
{ "seq_id" : 49972, "qsl_idx" : 20097, "data" : "BC030000" },
{ "seq_id" : 49973, "qsl_idx" : 18510, "data" : "82000000" },
{ "seq_id" : 49974, "qsl_idx" : 9694, "data" : "AC020000" },
{ "seq_id" : 49975, "qsl_idx" : 10916, "data" : "50000000" },
{ "seq_id" : 49976, "qsl_idx" : 46336, "data" : "3F030000" },
{ "seq_id" : 49977, "qsl_idx" : 40389, "data" : "8D000000" },
{ "seq_id" : 49978, "qsl_idx" : 9118, "data" : "17000000" },
{ "seq_id" : 49979, "qsl_idx" : 49538, "data" : "46030000" },
{ "seq_id" : 49980, "qsl_idx" : 22684, "data" : "25020000" },
{ "seq_id" : 49981, "qsl_idx" : 17210, "data" : "A8030000" },
{ "seq_id" : 49982, "qsl_idx" : 25815, "data" : "2D030000" },
{ "seq_id" : 49983, "qsl_idx" : 22436, "data" : "39010000" }
]
