[
{ "seq_id" : 160, "qsl_idx" : 8053, "data" : "4E000000" },
{ "seq_id" : 161, "qsl_idx" : 27987, "data" : "B6030000" },
{ "seq_id" : 162, "qsl_idx" : 6842, "data" : "22020000" },
{ "seq_id" : 163, "qsl_idx" : 48815, "data" : "DE020000" },
{ "seq_id" : 164, "qsl_idx" : 30262, "data" : "83000000" },
{ "seq_id" : 165, "qsl_idx" : 16463, "data" : "28000000" },
{ "seq_id" : 166, "qsl_idx" : 27323, "data" : "6C030000" },
{ "seq_id" : 167, "qsl_idx" : 20706, "data" : "93000000" },
{ "seq_id" : 168, "qsl_idx" : 8312, "data" : "E1020000" },
{ "seq_id" : 169, "qsl_idx" : 350, "data" : "89030000" },
{ "seq_id" : 170, "qsl_idx" : 4821, "data" : "19020000" },
{ "seq_id" : 171, "qsl_idx" : 37074, "data" : "E8000000" },
{ "seq_id" : 172, "qsl_idx" : 45533, "data" : "59020000" },
{ "seq_id" : 173, "qsl_idx" : 26449, "data" : "2B010000" },
{ "seq_id" : 174, "qsl_idx" : 8883, "data" : "CD010000" },
{ "seq_id" : 175, "qsl_idx" : 20684, "data" : "B9010000" },
{ "seq_id" : 176, "qsl_idx" : 18248, "data" : "FF010000" },
{ "seq_id" : 177, "qsl_idx" : 25977, "data" : "14030000" },
{ "seq_id" : 178, "qsl_idx" : 25356, "data" : "6B030000" },
{ "seq_id" : 179, "qsl_idx" : 28840, "data" : "BA030000" },
{ "seq_id" : 180, "qsl_idx" : 31544, "data" : "AA000000" },
{ "seq_id" : 181, "qsl_idx" : 16926, "data" : "E8020000" },
{ "seq_id" : 182, "qsl_idx" : 26648, "data" : "4D030000" },
{ "seq_id" : 183, "qsl_idx" : 16641, "data" : "C6000000" },
{ "seq_id" : 184, "qsl_idx" : 48941, "data" : "F3010000" },
{ "seq_id" : 185, "qsl_idx" : 44362, "data" : "59000000" },
{ "seq_id" : 186, "qsl_idx" : 24226, "data" : "2B000000" },
{ "seq_id" : 187, "qsl_idx" : 34902, "data" : "07020000" },
{ "seq_id" : 188, "qsl_idx" : 6702, "data" : "26010000" },
{ "seq_id" : 189, "qsl_idx" : 44257, "data" : "09010000" },
{ "seq_id" : 190, "qsl_idx" : 18487, "data" : "E2020000" },
{ "seq_id" : 191, "qsl_idx" : 9217, "data" : "8F010000" },
{ "seq_id" : 192, "qsl_idx" : 43099, "data" : "6C010000" },
{ "seq_id" : 193, "qsl_idx" : 46675, "data" : "8F020000" },
{ "seq_id" : 194, "qsl_idx" : 20681, "data" : "17030000" },
{ "seq_id" : 195, "qsl_idx" : 18192, "data" : "8D020000" },
{ "seq_id" : 196, "qsl_idx" : 3286, "data" : "21000000" },
{ "seq_id" : 197, "qsl_idx" : 3362, "data" : "AA000000" },
{ "seq_id" : 198, "qsl_idx" : 29842, "data" : "4D000000" },
{ "seq_id" : 199, "qsl_idx" : 22168, "data" : "D3010000" },
{ "seq_id" : 200, "qsl_idx" : 44532, "data" : "6D000000" },
{ "seq_id" : 201, "qsl_idx" : 43767, "data" : "35010000" },
{ "seq_id" : 202, "qsl_idx" : 6474, "data" : "B2030000" },
{ "seq_id" : 203, "qsl_idx" : 2513, "data" : "25000000" },
{ "seq_id" : 204, "qsl_idx" : 8388, "data" : "33020000" },
{ "seq_id" : 205, "qsl_idx" : 42059, "data" : "F0010000" },
{ "seq_id" : 206, "qsl_idx" : 23077, "data" : "87010000" },
{ "seq_id" : 207, "qsl_idx" : 4637, "data" : "26000000" },
{ "seq_id" : 208, "qsl_idx" : 43459, "data" : "67030000" },
{ "seq_id" : 209, "qsl_idx" : 2999, "data" : "75010000" },
{ "seq_id" : 210, "qsl_idx" : 23285, "data" : "66020000" },
{ "seq_id" : 211, "qsl_idx" : 4881, "data" : "81010000" },
{ "seq_id" : 212, "qsl_idx" : 1627, "data" : "79030000" },
{ "seq_id" : 213, "qsl_idx" : 37338, "data" : "B8000000" },
{ "seq_id" : 214, "qsl_idx" : 672, "data" : "08030000" },
{ "seq_id" : 215, "qsl_idx" : 25921, "data" : "79000000" },
{ "seq_id" : 216, "qsl_idx" : 46051, "data" : "17020000" },
{ "seq_id" : 217, "qsl_idx" : 31063, "data" : "64020000" },
{ "seq_id" : 218, "qsl_idx" : 29755, "data" : "4A000000" },
{ "seq_id" : 219, "qsl_idx" : 23098, "data" : "53000000" },
{ "seq_id" : 220, "qsl_idx" : 39298, "data" : "54000000" },
{ "seq_id" : 221, "qsl_idx" : 27568, "data" : "5D020000" },
{ "seq_id" : 222, "qsl_idx" : 36521, "data" : "BC020000" },
{ "seq_id" : 223, "qsl_idx" : 46959, "data" : "48010000" },
{ "seq_id" : 224, "qsl_idx" : 43920, "data" : "BD010000" },
{ "seq_id" : 225, "qsl_idx" : 19583, "data" : "82030000" },
{ "seq_id" : 226, "qsl_idx" : 9659, "data" : "E6000000" },
{ "seq_id" : 227, "qsl_idx" : 5227, "data" : "79000000" },
{ "seq_id" : 228, "qsl_idx" : 10955,

...

"D2020000" },
{ "seq_id" : 49933, "qsl_idx" : 16446, "data" : "80030000" },
{ "seq_id" : 49934, "qsl_idx" : 23345, "data" : "DD000000" },
{ "seq_id" : 49935, "qsl_idx" : 1994, "data" : "EF020000" },
{ "seq_id" : 49936, "qsl_idx" : 20820, "data" : "1C020000" },
{ "seq_id" : 49937, "qsl_idx" : 27072, "data" : "A7020000" },
{ "seq_id" : 49938, "qsl_idx" : 48278, "data" : "8B030000" },
{ "seq_id" : 49939, "qsl_idx" : 43668, "data" : "42030000" },
{ "seq_id" : 49940, "qsl_idx" : 27199, "data" : "13030000" },
{ "seq_id" : 49941, "qsl_idx" : 13184, "data" : "C5010000" },
{ "seq_id" : 49942, "qsl_idx" : 10645, "data" : "C9020000" },
{ "seq_id" : 49943, "qsl_idx" : 38805, "data" : "9D030000" },
{ "seq_id" : 49944, "qsl_idx" : 17721, "data" : "FA000000" },
{ "seq_id" : 49945, "qsl_idx" : 34841, "data" : "CB030000" },
{ "seq_id" : 49946, "qsl_idx" : 14755, "data" : "1E020000" },
{ "seq_id" : 49947, "qsl_idx" : 15706, "data" : "9C010000" },
{ "seq_id" : 49948, "qsl_idx" : 1637, "data" : "7C020000" },
{ "seq_id" : 49949, "qsl_idx" : 47936, "data" : "AA030000" },
{ "seq_id" : 49950, "qsl_idx" : 11134, "data" : "AB020000" },
{ "seq_id" : 49951, "qsl_idx" : 45548, "data" : "2D010000" },
{ "seq_id" : 49952, "qsl_idx" : 24123, "data" : "6C030000" },
{ "seq_id" : 49953, "qsl_idx" : 23138, "data" : "AB030000" },
{ "seq_id" : 49954, "qsl_idx" : 30458, "data" : "32010000" },
{ "seq_id" : 49955, "qsl_idx" : 39511, "data" : "58020000" },
{ "seq_id" : 49956, "qsl_idx" : 16588, "data" : "D5000000" },
{ "seq_id" : 49957, "qsl_idx" : 4194, "data" : "FD010000" },
{ "seq_id" : 49958, "qsl_idx" : 47516, "data" : "7C020000" },
{ "seq_id" : 49959, "qsl_idx" : 10074, "data" : "18010000" },
{ "seq_id" : 49960, "qsl_idx" : 33176, "data" : "16010000" },
{ "seq_id" : 49961, "qsl_idx" : 11451, "data" : "AB020000" },
{ "seq_id" : 49962, "qsl_idx" : 3024, "data" : "72020000" },
{ "seq_id" : 49963, "qsl_idx" : 49697, "data" : "48030000" },
{ "seq_id" : 49964, "qsl_idx" : 40142, "data" : "34030000" },
{ "seq_id" : 49965, "qsl_idx" : 5841, "data" : "D9000000" },
{ "seq_id" : 49966, "qsl_idx" : 41523, "data" : "F5000000" },
{ "seq_id" : 49967, "qsl_idx" : 7997, "data" : "1B000000" },
{ "seq_id" : 49968, "qsl_idx" : 49216, "data" : "69000000" },
{ "seq_id" : 49969, "qsl_idx" : 49881, "data" : "D6030000" },
{ "seq_id" : 49970, "qsl_idx" : 31290, "data" : "3A030000" },
{ "seq_id" : 49971, "qsl_idx" : 45052, "data" : "FB020000" },
{ "seq_id" : 49972, "qsl_idx" : 20097, "data" : "BC030000" },
{ "seq_id" : 49973, "qsl_idx" : 18510, "data" : "82000000" },
{ "seq_id" : 49974, "qsl_idx" : 9694, "data" : "03020000" },
{ "seq_id" : 49975, "qsl_idx" : 10916, "data" : "50000000" },
{ "seq_id" : 49976, "qsl_idx" : 46336, "data" : "3F030000" },
{ "seq_id" : 49977, "qsl_idx" : 40389, "data" : "8D000000" },
{ "seq_id" : 49978, "qsl_idx" : 9118, "data" : "17000000" },
{ "seq_id" : 49979, "qsl_idx" : 49538, "data" : "46030000" },
{ "seq_id" : 49980, "qsl_idx" : 22684, "data" : "25020000" },
{ "seq_id" : 49981, "qsl_idx" : 17210, "data" : "A8030000" },
{ "seq_id" : 49982, "qsl_idx" : 25815, "data" : "2D030000" },
{ "seq_id" : 49983, "qsl_idx" : 22436, "data" : "39010000" },
{ "seq_id" : 49984, "qsl_idx" : 45811, "data" : "1C020000" },
{ "seq_id" : 49985, "qsl_idx" : 28687, "data" : "1E030000" },
{ "seq_id" : 49986, "qsl_idx" : 39909, "data" : "62030000" },
{ "seq_id" : 49987, "qsl_idx" : 44561, "data" : "ED010000" },
{ "seq_id" : 49988, "qsl_idx" : 21836, "data" : "24030000" },
{ "seq_id" : 49989, "qsl_idx" : 33201, "data" : "D6020000" },
{ "seq_id" : 49990, "qsl_idx" : 41421, "data" : "F3000000" },
{ "seq_id" : 49991, "qsl_idx" : 33105, "data" : "B3010000" },
{ "seq_id" : 49992, "qsl_idx" : 32687, "data" : "A7020000" },
{ "seq_id" : 49993, "qsl_idx" : 5991, "data" : "35030000" },
{ "seq_id" : 49994, "qsl_idx" : 31009, "data" : "D3010000" },
{ "seq_id" : 49995, "qsl_idx" : 13813, "data" : "EF000000" },
{ "seq_id" : 49996, "qsl_idx" : 3183, "data" : "19030000" },
{ "seq_id" : 49997, "qsl_idx" : 10257, "data" : "5A000000" },
{ "seq_id" : 49998, "qsl_idx" : 6432, "data" : "7F010000" }
]
